fms_mo/__init__.py
fms_model_optimization-0.0.0.dist-info/METADATA
fms_model_optimization-0.0.0.dist-info/WHEEL
fms_model_optimization-0.0.0.dist-info/top_level.txt
fms_model_optimization-0.0.0.dist-info/RECORD
