Metadata-Version: 2.1
Name: fms-model-optimization
Version: 0.0.0
Summary: Quantization Techniques
License: Apache-2.0
Classifier: License :: OSI Approved :: Apache Software License
Requires-Python: >=3.8
